comp_reporting_app/__init__.py
comp_reporting_app-0.1.1.dist-info/METADATA
comp_reporting_app-0.1.1.dist-info/WHEEL
comp_reporting_app-0.1.1.dist-info/RECORD
